django_template_helpers-0.2.0.dist-info/METADATA
django_template_helpers-0.2.0.dist-info/RECORD
django_template_helpers-0.2.0.dist-info/WHEEL
django_template_helpers-0.2.0.dist-info/top_level.txt
template_helpers/__init__.py
template_helpers/context_processors.py
template_helpers/views.py
template_helpers/templatetags/__init__.py
template_helpers/templatetags/template_helpers.py
