Metadata-Version: 2.1
Name: django-template-helpers
Version: 0.2.0
Summary: django-template-helpers provides template tags to add missing features to the Django template language.
Home-page: https://github.com/moccu/django-template-helpers
Author: Moccu GmbH & Co. KG
Author-email: info@moccu.com
License: UNKNOWN
Project-URL: Bug Reports, https://github.com/moccu/django-template-helpers/issues
Project-URL: Source, https://github.com/moccu/django-template-helpers
Keywords: django templates
Platform: UNKNOWN
Classifier: Development Status :: 4 - Beta
Classifier: Environment :: Web Environment
Classifier: Framework :: Django
Classifier: Intended Audience :: Developers
Classifier: License :: OSI Approved :: MIT License
Classifier: Programming Language :: Python :: 3
Classifier: Programming Language :: Python :: 3.6
